pdfparser/__init__.py
pdfparser/poppler.cpp
pdfparser/poppler.cpython-37m-darwin.so
pdfparser/poppler.pyx
pdfparser_rossum-1.3.1.dist-info/METADATA
pdfparser_rossum-1.3.1.dist-info/WHEEL
pdfparser_rossum-1.3.1.dist-info/top_level.txt
pdfparser_rossum-1.3.1.dist-info/RECORD
