Metadata-Version: 2.1
Name: pdfparser-rossum
Version: 1.3.1
Summary: python bindings for poppler
Home-page: https://github.com/rossumai/pdfparser
Author: UNKNOWN
Author-email: UNKNOWN
License: UNKNOWN
Keywords: poppler pdf parsing rendering mining extracting
Platform: UNKNOWN
Classifier: Development Status :: 5 - Production/Stable
Classifier: Intended Audience :: Developers
Classifier: Topic :: Text Processing
Classifier: License :: OSI Approved :: GNU General Public License v3 (GPLv3)
Classifier: Programming Language :: Python :: 2.7
Classifier: Programming Language :: Python :: 3.5
Classifier: Programming Language :: Python :: 3.6
Requires-Dist: pycairo (>=0.16.0)
